ttsim/__init__.py
ttsim/_version.py
ttsim/entry_point.py
ttsim/main_args.py
ttsim/main_target.py
ttsim/params-schema.json
ttsim/testing_utils.py
ttsim/typing.py
ttsim/interface_dag_elements/__init__.py
ttsim/interface_dag_elements/automatically_added_functions.py
ttsim/interface_dag_elements/backend.py
ttsim/interface_dag_elements/data_converters.py
ttsim/interface_dag_elements/dates.py
ttsim/interface_dag_elements/fail_if.py
ttsim/interface_dag_elements/input_data.py
ttsim/interface_dag_elements/interface_node_objects.py
ttsim/interface_dag_elements/labels.py
ttsim/interface_dag_elements/num_segments.py
ttsim/interface_dag_elements/orig_policy_objects.py
ttsim/interface_dag_elements/policy_environment.py
ttsim/interface_dag_elements/processed_data.py
ttsim/interface_dag_elements/raw_results.py
ttsim/interface_dag_elements/results.py
ttsim/interface_dag_elements/shared.py
ttsim/interface_dag_elements/specialized_environment.py
ttsim/interface_dag_elements/specialized_environment_for_plotting_and_templates.py
ttsim/interface_dag_elements/templates.py
ttsim/interface_dag_elements/tt_function.py
ttsim/interface_dag_elements/tt_targets.py
ttsim/interface_dag_elements/warn_if.py
ttsim/plot/__init__.py
ttsim/plot/dag/__init__.py
ttsim/plot/dag/interface.py
ttsim/plot/dag/shared.py
ttsim/plot/dag/tt.py
ttsim/tt/__init__.py
ttsim/tt/aggregation.py
ttsim/tt/aggregation_jax.py
ttsim/tt/aggregation_numpy.py
ttsim/tt/column_objects_param_function.py
ttsim/tt/param_objects.py
ttsim/tt/piecewise_polynomial.py
ttsim/tt/rounding.py
ttsim/tt/shared.py
ttsim/tt/vectorization.py
ttsim_backend-1.1.0.dist-info/METADATA
ttsim_backend-1.1.0.dist-info/WHEEL
ttsim_backend-1.1.0.dist-info/licenses/LICENSE
ttsim_backend-1.1.0.dist-info/RECORD
