Metadata-Version: 2.4
Name: ttsim-backend
Version: 1.1.0
Summary: code powering Taxes and Transfers SIMulators
Project-URL: Repository, https://github.com/ttsim-dev/ttsim
Project-URL: Changelog, https://github.com/ttsim-dev/ttsim/CHANGES.md
Project-URL: Documentation, https://gettsim.readthedocs.io
Project-URL: Github, https://github.com/ttsim-dev/ttsim
Project-URL: Tracker, https://github.com/ttsim-dev/ttsim/issues
Author: Marvin Immesberger
Author-email: Hans-Martin von Gaudecker <hmgaudecker@uni-bonn.de>
Maintainer: Marvin Immesberger
Maintainer-email: Hans-Martin von Gaudecker <hmgaudecker@uni-bonn.de>
License:                     GNU AFFERO GENERAL PUBLIC LICENSE
License-File: LICENSE
Keywords: Benefits,Economics,Pensions,Taxes,Transfers
Classifier: Intended Audience :: Science/Research
Classifier: License :: OSI Approved :: GNU Affero General Public License v3
Classifier: License :: OSI Approved :: GNU General Public License v3 (GPLv3)
Classifier: Operating System :: MacOS :: MacOS X
Classifier: Operating System :: Microsoft :: Windows
Classifier: Operating System :: POSIX
Classifier: Operating System :: Unix
Classifier: Programming Language :: Python :: 3
Classifier: Programming Language :: Python :: 3 :: Only
Requires-Python: >=3.11
Requires-Dist: dags>=0.4.1
Requires-Dist: ipywidgets
Requires-Dist: networkx>=3.5
Requires-Dist: numpy
Requires-Dist: numpy-groupies
Requires-Dist: openpyxl
Requires-Dist: optree>=0.16.0
Requires-Dist: pandas
Requires-Dist: plotly>=6.2.0
Requires-Dist: pygments
Requires-Dist: pygraphviz
Requires-Dist: pytest
Requires-Dist: pyyaml
